bioseq/__init__.py
bioseq/_sequence.py
bioseq/algorithm.cpython-38-x86_64-linux-gnu.so
bioseq/algorithm.pyi
bioseq/config.py
bioseq/utils.py
bioseq/algorithm/algorithm.h
test/__init__.py
test/test_bioseq.py
test/test_config.py
test/test_utils.py
BioSequences-1.1.5.dist-info/LICENSE
BioSequences-1.1.5.dist-info/METADATA
BioSequences-1.1.5.dist-info/WHEEL
BioSequences-1.1.5.dist-info/top_level.txt
BioSequences-1.1.5.dist-info/RECORD
