Metadata-Version: 2.1
Name: BioSequences
Version: 1.1.5
Summary: Tools to analysis biology sequence
Home-page: https://github.com/Dragon-GCS/BioSequence
Author: Dragon
Author-email: 878173121@qq.com
License: GPL License
Project-URL: Bug Tracker, https://github.com/Dragon-GCS/BioSequence/issues
Keywords: biology,analysis
Platform: UNKNOWN
Classifier: Topic :: Scientific/Engineering :: Bio-Informatics
Classifier: Environment :: Console
Classifier: License :: OSI Approved :: GNU General Public License (GPL)
Classifier: Intended Audience :: Science/Research
Classifier: Operating System :: OS Independent
Classifier: Natural Language :: Chinese (Simplified)
Classifier: Natural Language :: English
Classifier: Programming Language :: Python :: 3.8
